[
        {
                "id": 1,
                "description": "large",
                "name": "ሻይ",
                "catagory": "tikus",
                "special_instructions": "special drinks instruction",
                "price": {
                        "birr": 119,
                        "cent": 99
                }
        },
        {
                "id": 2,
                "description": "large",
                "name": "ቡና",
                "catagory": "tikus",
                "price": {
                        "birr": 119,
                        "cent": 99
                }
        },
        {
                "id": 3,
                "description": "large",
                "name": "ወተት",
                "catagory": "tikus",
                "price": {
                        "birr": 119,
                        "cent": 99
                }
        },
        {
                "id": 4,
                "description": "large",
                "name": "ለውዝ",
                "catagory": "tikus",
                "price": {
                        "birr": 119,
                        "cent": 99
                }
        },
        {
                "id": 5,
                "description": "large",
                "name": "ማኪያቶ",
                "catagory": "tikus",
                "price": {
                        "birr": 119,
                        "cent": 99
                }
        },
        {
                "id": 6,
                "description": "large",
                "name": "ቀሽር",
                "catagory": "tikus",
                "price": {
                        "birr": 119,
                        "cent": 99
                }
        }
]